<?xml version="1.0" encoding="UTF-8"?>
<SOAConfigPlan xmlns:jca="http://platform.integration.oracle/blocks/adapter/fw/metadata" xmlns:wsp="http://schemas.xmlsoap.org/ws/2004/09/policy" xmlns:orawsp="http://schemas.oracle.com/ws/2006/01/policy" xmlns:edl="http://schemas.oracle.com/events/edl" xmlns="http://schemas.oracle.com/soa/configplan">
   <composite name="CreateDeliveryScheduleOTMReqABCS">
      <!--Add search and replace rules for the import section of a composite
	Example:
	<searchReplace>
		<search>http://my-dev-server</search>
		<replace>http://my-test-server</replace>
	<searchReplace>
	<searchReplace>
		<search>8888</search>
		<replace>8889</replace>
	<searchReplace>-->
      <import>
         <searchReplace>
            <search/>
            <replace/>
         </searchReplace>
      </import>
      <service name="CreateDeliveryScheduleOTMReqABCS">
         <!--Add search and replace rules for the binding properties-->
         <binding type="ws">
            <attribute name="port">
               <replace>ikea.com/system/iip/CreateDeliveryScheduleOTMReqABCSService/1.0/#wsdl.endpoint(CreateDeliveryScheduleOTMReqABCS/CreateDeliveryScheduleOTMReqABCS)</replace>
            </attribute>
            <property name="weblogic.wsee.wsat.transaction.flowOption">
               <replace>NEVER</replace>
            </property>
         </binding>
      </service>
      <property name="oracle.composite.faultPolicyFile">
         <replace>oramds:/apps/AIAMetaData/faultPolicies/fault-policies.xml</replace>
      </property>
      <property name="oracle.composite.faultBindingFile">
         <replace>oramds:/apps/AIAMetaData/faultPolicies/fault-bindings.xml</replace>
      </property>
      <!--Add search and replace rules for the component properties
	For components and service/reference bindings, you can add policy references.
	Example:
	<component name="*">
		<wsp:PolicyReference orawsp:category="management" orawsp:status="enabled" URI="oracle/log_policy"/>
	</component>-->
      <component name="CreateDeliveryScheduleOTMReqABCSProcess">
         <property name="bpel.config.transaction">
            <replace>required</replace>
         </property>
         <property name="bpel.preference.reportToBAM">
            <replace>true</replace>
         </property>
         <property name="configuration.sensorLocation">
            <replace>BPEL/CreateDeliveryScheduleOTMReqABCSProcess_sensor.xml</replace>
         </property>
         <property name="configuration.sensorActionLocation">
            <replace>BPEL/CreateDeliveryScheduleOTMReqABCSProcess_sensorAction.xml</replace>
         </property>
         <property name="bpel.config.oneWayDeliveryPolicy">
            <replace>sync</replace>
         </property>
         <property name="bpel.preference.tracingEnabled">
            <replace>true</replace>
         </property>
         <property name="bpel.preference.reportToBAMEntry">
            <replace>${CreateDeliveryScheduleOTMReqABCS.reportToBAMEntry}</replace>
         </property>
         <property name="bpel.preference.reportToBAMExit">
            <replace>${CreateDeliveryScheduleOTMReqABCS.reportToBAMExit}</replace>
         </property>
         <property name="bpel.preference.reportToBAMError">
            <replace>${CreateDeliveryScheduleOTMReqABCS.reportToBAMError}</replace>
         </property>
      </component>
      <reference name="IIPAsyncErrorHandlingProcess">
         <!--Add search and replace rules for the binding properties-->
         <binding type="ws">
            <attribute name="port">
               <replace>ikea.com/system/iip/IIPAsyncErrorHandlingService/1.0/#wsdl.endpoint(IIPAsyncErrorHandlingProcess/IIPAsyncErrorHandlingProcess)</replace>
            </attribute>
            <attribute name="location">
               <replace>${middleware.errorhandling.url}</replace>
            </attribute>
            <property name="weblogic.wsee.wsat.transaction.flowOption">
               <replace>WSDLDriven</replace>
            </property>
         </binding>
      </reference>
      <reference name="DeliveryScheduleEBS">
         <!--Add search and replace rules for the binding properties-->
         <binding type="ws">
            <attribute name="port">
               <replace>ikea.com/system/iip/DeliveryScheduleEnterpriseService/1.0/#wsdl.endpoint(DeliveryScheduleEBS/DeliveryScheduleEBS)</replace>
            </attribute>
            <attribute name="location">
               <replace>${DeliveryScheduleEBS.url}</replace>
            </attribute>
            <property name="csf-key">
               <replace>oitp-service-account</replace>
            </property>
            <property name="weblogic.wsee.wsat.transaction.flowOption">
               <replace>WSDLDriven</replace>
            </property>
         </binding>
      </reference>
      <reference name="CreateDeliveryScheduleOTMRef1">
         <!--Add search and replace rules for the binding properties-->
         <binding type="ws">
            <attribute name="port">
               <replace>http://xmlns.oracle.com/apps/otm/TransmissionService#wsdl.interface(TransmissionService/Transmission)</replace>
            </attribute>
            <attribute name="location">
               <replace>${CreateDeliveryScheduleOTMRef.url}</replace>
            </attribute>
            <property name="csf-key">
               <replace>com.ikea.stms.itm</replace>
            </property>
            <property name="reference.priority">
               <replace>2</replace>
            </property>
         </binding>
      </reference>
   </composite>
   <!--To configure monitor.config: 
	<property name="enabled"><replace>true</replace></property>
	<property name="dataObjectsFolder"><searchReplace><search>mydev</search><replace>myproduction</replace></searchReplace></property>
	
	sample properties to configure for adapter: 
	<jca:property name="QueueName"><replace>medmq1</replace></jca:property>
	
	To add search and replace rules for wsdls, xsd and jca files
	Example:
	<searchReplace>
		<search>http://my-dev-server</search>
		<replace>http://my-test-server</replace>
	<searchReplace>
	<searchReplace>
		<search>8888</search>
		<replace>8889</replace>
	<searchReplace>
	-->
   <wsdlAndSchema name="Schemas/SubsitutionElement.xsd|WSDLs/CreateDeliveryScheduleOTMRef.wsdl|WSDLs/CreateDeliveryScheduleOTMReqABCSRef.wsdl|WSDLs/DeliveryScheduleEBSRef.wsdl|wsm-assembly.xml">
      <searchReplace>
         <search/>
         <replace/>
      </searchReplace>
   </wsdlAndSchema>
</SOAConfigPlan>
